{
    "0": {
        "x": [
            985,
            1022,
            1022,
            985
        ],
        "y": [
            286,
            286,
            330,
            330
        ]
    },
    "1": {
        "x": [
            935,
            948,
            948,
            935
        ],
        "y": [
            272,
            272,
            291,
            291
        ]
    },
    "2": {
        "x": [
            792,
            838,
            838,
            792
        ],
        "y": [
            225,
            225,
            280,
            280
        ]
    },
    "3": {
        "x": [
            529,
            584,
            584,
            529
        ],
        "y": [
            200,
            200,
            261,
            261
        ]
    },
    "4": {
        "x": [
            379,
            398,
            398,
            379
        ],
        "y": [
            314,
            314,
            341,
            341
        ]
    },
    "5": {
        "x": [
            358,
            379,
            379,
            358
        ],
        "y": [
            321,
            321,
            350,
            350
        ]
    },
    "6": {
        "x": [
            314,
            333,
            333,
            314
        ],
        "y": [
            326,
            326,
            350,
            350
        ]
    },
    "7": {
        "x": [
            175,
            198,
            198,
            175
        ],
        "y": [
            313,
            313,
            339,
            339
        ]
    },
    "8": {
        "x": [
            59,
            103,
            103,
            59
        ],
        "y": [
            259,
            259,
            317,
            317
        ]
    },
    "9": {
        "x": [
            0,
            15,
            15,
            0
        ],
        "y": [
            325,
            325,
            354,
            354
        ]
    },
    "10": {
        "x": [
            960,
            979,
            979,
            960
        ],
        "y": [
            352,
            352,
            377,
            377
        ]
    },
    "11": {
        "x": [
            47,
            69,
            69,
            47
        ],
        "y": [
            323,
            323,
            349,
            349
        ]
    }
}