{
    "0": {
        "x": [
            694,
            808,
            808,
            694
        ],
        "y": [
            89,
            89,
            242,
            242
        ]
    },
    "1": {
        "x": [
            511,
            591,
            591,
            511
        ],
        "y": [
            276,
            276,
            413,
            413
        ]
    },
    "2": {
        "x": [
            436,
            511,
            511,
            436
        ],
        "y": [
            241,
            241,
            352,
            352
        ]
    },
    "3": {
        "x": [
            338,
            404,
            404,
            338
        ],
        "y": [
            304,
            304,
            407,
            407
        ]
    },
    "4": {
        "x": [
            256,
            308,
            308,
            256
        ],
        "y": [
            423,
            423,
            506,
            506
        ]
    },
    "5": {
        "x": [
            245,
            283,
            283,
            245
        ],
        "y": [
            400,
            400,
            459,
            459
        ]
    },
    "6": {
        "x": [
            146,
            186,
            186,
            146
        ],
        "y": [
            565,
            565,
            625,
            625
        ]
    },
    "7": {
        "x": [
            245,
            278,
            278,
            245
        ],
        "y": [
            459,
            459,
            504,
            504
        ]
    }
}