{
    "0": {
        "x": [
            247,
            340,
            340,
            247
        ],
        "y": [
            214,
            214,
            339,
            339
        ]
    },
    "1": {
        "x": [
            387,
            492,
            492,
            387
        ],
        "y": [
            128,
            128,
            261,
            261
        ]
    },
    "2": {
        "x": [
            556,
            678,
            678,
            556
        ],
        "y": [
            292,
            292,
            407,
            407
        ]
    },
    "3": {
        "x": [
            595,
            641,
            641,
            595
        ],
        "y": [
            150,
            150,
            243,
            243
        ]
    },
    "4": {
        "x": [
            708,
            747,
            747,
            708
        ],
        "y": [
            168,
            168,
            243,
            243
        ]
    },
    "5": {
        "x": [
            875,
            928,
            928,
            875
        ],
        "y": [
            144,
            144,
            232,
            232
        ]
    },
    "6": {
        "x": [
            895,
            934,
            934,
            895
        ],
        "y": [
            227,
            227,
            273,
            273
        ]
    },
    "7": {
        "x": [
            59,
            100,
            100,
            59
        ],
        "y": [
            271,
            271,
            335,
            335
        ]
    }
}