{
    "0": {
        "x": [
            85,
            337,
            337,
            85
        ],
        "y": [
            283,
            283,
            619,
            619
        ]
    },
    "1": {
        "x": [
            646,
            813,
            813,
            646
        ],
        "y": [
            244,
            244,
            471,
            471
        ]
    },
    "2": {
        "x": [
            430,
            497,
            497,
            430
        ],
        "y": [
            1004,
            1004,
            1096,
            1096
        ]
    },
    "3": {
        "x": [
            911,
            965,
            965,
            911
        ],
        "y": [
            905,
            905,
            980,
            980
        ]
    },
    "4": {
        "x": [
            907,
            964,
            964,
            907
        ],
        "y": [
            1192,
            1192,
            1274,
            1274
        ]
    }
}