{
    "0": {
        "x": [
            512,
            598,
            598,
            512
        ],
        "y": [
            128,
            128,
            244,
            244
        ]
    },
    "1": {
        "x": [
            212,
            312,
            312,
            212
        ],
        "y": [
            72,
            72,
            220,
            220
        ]
    },
    "2": {
        "x": [
            640,
            754,
            754,
            640
        ],
        "y": [
            112,
            112,
            234,
            234
        ]
    }
}