{
    "0": {
        "x": [
            583,
            629,
            629,
            583
        ],
        "y": [
            416,
            416,
            469,
            469
        ]
    },
    "1": {
        "x": [
            239,
            286,
            286,
            239
        ],
        "y": [
            406,
            406,
            460,
            460
        ]
    },
    "2": {
        "x": [
            867,
            888,
            888,
            867
        ],
        "y": [
            674,
            674,
            700,
            700
        ]
    },
    "3": {
        "x": [
            808,
            827,
            827,
            808
        ],
        "y": [
            675,
            675,
            699,
            699
        ]
    },
    "4": {
        "x": [
            708,
            727,
            727,
            708
        ],
        "y": [
            651,
            651,
            675,
            675
        ]
    }
}