{
    "0": {
        "x": [
            518,
            574,
            574,
            518
        ],
        "y": [
            128,
            128,
            199,
            199
        ]
    },
    "1": {
        "x": [
            280,
            334,
            334,
            280
        ],
        "y": [
            75,
            75,
            148,
            148
        ]
    },
    "2": {
        "x": [
            146,
            202,
            202,
            146
        ],
        "y": [
            83,
            83,
            166,
            166
        ]
    },
    "3": {
        "x": [
            73,
            127,
            127,
            73
        ],
        "y": [
            90,
            90,
            174,
            174
        ]
    }
}