{
    "0": {
        "x": [
            69,
            197,
            197,
            69
        ],
        "y": [
            81,
            81,
            247,
            247
        ]
    },
    "1": {
        "x": [
            429,
            466,
            466,
            429
        ],
        "y": [
            215,
            215,
            256,
            256
        ]
    },
    "2": {
        "x": [
            564,
            600,
            600,
            564
        ],
        "y": [
            267,
            267,
            303,
            303
        ]
    },
    "3": {
        "x": [
            485,
            514,
            514,
            485
        ],
        "y": [
            419,
            419,
            454,
            454
        ]
    },
    "4": {
        "x": [
            379,
            416,
            416,
            379
        ],
        "y": [
            295,
            295,
            338,
            338
        ]
    },
    "5": {
        "x": [
            600,
            627,
            627,
            600
        ],
        "y": [
            477,
            477,
            503,
            503
        ]
    },
    "6": {
        "x": [
            643,
            671,
            671,
            643
        ],
        "y": [
            416,
            416,
            444,
            444
        ]
    },
    "7": {
        "x": [
            761,
            778,
            778,
            761
        ],
        "y": [
            404,
            404,
            427,
            427
        ]
    },
    "8": {
        "x": [
            788,
            815,
            815,
            788
        ],
        "y": [
            243,
            243,
            275,
            275
        ]
    },
    "9": {
        "x": [
            859,
            887,
            887,
            859
        ],
        "y": [
            195,
            195,
            231,
            231
        ]
    },
    "10": {
        "x": [
            925,
            948,
            948,
            925
        ],
        "y": [
            406,
            406,
            434,
            434
        ]
    },
    "11": {
        "x": [
            768,
            868,
            868,
            768
        ],
        "y": [
            578,
            578,
            703,
            703
        ]
    },
    "12": {
        "x": [
            209,
            268,
            268,
            209
        ],
        "y": [
            499,
            499,
            569,
            569
        ]
    },
    "13": {
        "x": [
            87,
            156,
            156,
            87
        ],
        "y": [
            415,
            415,
            489,
            489
        ]
    },
    "14": {
        "x": [
            739,
            778,
            778,
            739
        ],
        "y": [
            67,
            67,
            114,
            114
        ]
    },
    "15": {
        "x": [
            811,
            842,
            842,
            811
        ],
        "y": [
            114,
            114,
            149,
            149
        ]
    },
    "16": {
        "x": [
            933,
            961,
            961,
            933
        ],
        "y": [
            114,
            114,
            149,
            149
        ]
    },
    "17": {
        "x": [
            880,
            911,
            911,
            880
        ],
        "y": [
            44,
            44,
            86,
            86
        ]
    },
    "18": {
        "x": [
            914,
            945,
            945,
            914
        ],
        "y": [
            208,
            208,
            240,
            240
        ]
    }
}