{
    "0": {
        "x": [
            416,
            444,
            444,
            416
        ],
        "y": [
            102,
            102,
            133,
            133
        ]
    },
    "1": {
        "x": [
            489,
            516,
            516,
            489
        ],
        "y": [
            106,
            106,
            140,
            140
        ]
    },
    "2": {
        "x": [
            542,
            569,
            569,
            542
        ],
        "y": [
            109,
            109,
            140,
            140
        ]
    },
    "3": {
        "x": [
            569,
            603,
            603,
            569
        ],
        "y": [
            162,
            162,
            203,
            203
        ]
    },
    "4": {
        "x": [
            522,
            552,
            552,
            522
        ],
        "y": [
            160,
            160,
            199,
            199
        ]
    },
    "5": {
        "x": [
            632,
            664,
            664,
            632
        ],
        "y": [
            179,
            179,
            215,
            215
        ]
    },
    "6": {
        "x": [
            478,
            513,
            513,
            478
        ],
        "y": [
            225,
            225,
            268,
            268
        ]
    },
    "7": {
        "x": [
            471,
            501,
            501,
            471
        ],
        "y": [
            177,
            177,
            214,
            214
        ]
    },
    "8": {
        "x": [
            393,
            419,
            419,
            393
        ],
        "y": [
            152,
            152,
            181,
            181
        ]
    },
    "9": {
        "x": [
            377,
            409,
            409,
            377
        ],
        "y": [
            197,
            197,
            230,
            230
        ]
    },
    "10": {
        "x": [
            359,
            382,
            382,
            359
        ],
        "y": [
            171,
            171,
            202,
            202
        ]
    },
    "11": {
        "x": [
            325,
            357,
            357,
            325
        ],
        "y": [
            202,
            202,
            238,
            238
        ]
    },
    "12": {
        "x": [
            262,
            293,
            293,
            262
        ],
        "y": [
            198,
            198,
            235,
            235
        ]
    },
    "13": {
        "x": [
            272,
            309,
            309,
            272
        ],
        "y": [
            246,
            246,
            291,
            291
        ]
    },
    "14": {
        "x": [
            670,
            706,
            706,
            670
        ],
        "y": [
            173,
            173,
            214,
            214
        ]
    },
    "15": {
        "x": [
            744,
            780,
            780,
            744
        ],
        "y": [
            204,
            204,
            243,
            243
        ]
    },
    "16": {
        "x": [
            779,
            818,
            818,
            779
        ],
        "y": [
            168,
            168,
            208,
            208
        ]
    },
    "17": {
        "x": [
            818,
            865,
            865,
            818
        ],
        "y": [
            142,
            142,
            189,
            189
        ]
    },
    "18": {
        "x": [
            912,
            964,
            964,
            912
        ],
        "y": [
            141,
            141,
            193,
            193
        ]
    },
    "19": {
        "x": [
            379,
            415,
            415,
            379
        ],
        "y": [
            357,
            357,
            392,
            392
        ]
    },
    "20": {
        "x": [
            492,
            531,
            531,
            492
        ],
        "y": [
            352,
            352,
            394,
            394
        ]
    },
    "21": {
        "x": [
            602,
            634,
            634,
            602
        ],
        "y": [
            327,
            327,
            369,
            369
        ]
    },
    "22": {
        "x": [
            744,
            779,
            779,
            744
        ],
        "y": [
            378,
            378,
            435,
            435
        ]
    },
    "23": {
        "x": [
            187,
            223,
            223,
            187
        ],
        "y": [
            196,
            196,
            236,
            236
        ]
    },
    "24": {
        "x": [
            202,
            241,
            241,
            202
        ],
        "y": [
            314,
            314,
            361,
            361
        ]
    },
    "25": {
        "x": [
            121,
            160,
            160,
            121
        ],
        "y": [
            249,
            249,
            294,
            294
        ]
    },
    "26": {
        "x": [
            114,
            156,
            156,
            114
        ],
        "y": [
            428,
            428,
            477,
            477
        ]
    },
    "27": {
        "x": [
            30,
            70,
            70,
            30
        ],
        "y": [
            242,
            242,
            281,
            281
        ]
    }
}