{
    "0": {
        "x": [
            92,
            131,
            131,
            92
        ],
        "y": [
            55,
            55,
            101,
            101
        ]
    },
    "1": {
        "x": [
            199,
            236,
            236,
            199
        ],
        "y": [
            71,
            71,
            110,
            110
        ]
    },
    "2": {
        "x": [
            199,
            227,
            227,
            199
        ],
        "y": [
            31,
            31,
            64,
            64
        ]
    },
    "3": {
        "x": [
            301,
            331,
            331,
            301
        ],
        "y": [
            15,
            15,
            48,
            48
        ]
    },
    "4": {
        "x": [
            340,
            367,
            367,
            340
        ],
        "y": [
            62,
            62,
            101,
            101
        ]
    },
    "5": {
        "x": [
            400,
            428,
            428,
            400
        ],
        "y": [
            79,
            79,
            116,
            116
        ]
    },
    "6": {
        "x": [
            404,
            431,
            431,
            404
        ],
        "y": [
            30,
            30,
            65,
            65
        ]
    },
    "7": {
        "x": [
            497,
            522,
            522,
            497
        ],
        "y": [
            151,
            151,
            185,
            185
        ]
    },
    "8": {
        "x": [
            585,
            609,
            609,
            585
        ],
        "y": [
            77,
            77,
            111,
            111
        ]
    },
    "9": {
        "x": [
            631,
            652,
            652,
            631
        ],
        "y": [
            105,
            105,
            131,
            131
        ]
    },
    "10": {
        "x": [
            627,
            647,
            647,
            627
        ],
        "y": [
            23,
            23,
            49,
            49
        ]
    },
    "11": {
        "x": [
            682,
            698,
            698,
            682
        ],
        "y": [
            56,
            56,
            82,
            82
        ]
    },
    "12": {
        "x": [
            713,
            731,
            731,
            713
        ],
        "y": [
            84,
            84,
            111,
            111
        ]
    },
    "13": {
        "x": [
            682,
            704,
            704,
            682
        ],
        "y": [
            107,
            107,
            136,
            136
        ]
    },
    "14": {
        "x": [
            772,
            814,
            814,
            772
        ],
        "y": [
            67,
            67,
            118,
            118
        ]
    },
    "15": {
        "x": [
            827,
            843,
            843,
            827
        ],
        "y": [
            61,
            61,
            82,
            82
        ]
    },
    "16": {
        "x": [
            921,
            941,
            941,
            921
        ],
        "y": [
            26,
            26,
            67,
            67
        ]
    },
    "17": {
        "x": [
            601,
            621,
            621,
            601
        ],
        "y": [
            58,
            58,
            83,
            83
        ]
    }
}