{
    "0": {
        "x": [
            495,
            522,
            522,
            495
        ],
        "y": [
            211,
            211,
            242,
            242
        ]
    },
    "1": {
        "x": [
            837,
            845,
            845,
            837
        ],
        "y": [
            351,
            351,
            361,
            361
        ]
    },
    "2": {
        "x": [
            939,
            945,
            945,
            939
        ],
        "y": [
            352,
            352,
            360,
            360
        ]
    },
    "3": {
        "x": [
            959,
            965,
            965,
            959
        ],
        "y": [
            351,
            351,
            359,
            359
        ]
    },
    "4": {
        "x": [
            987,
            992,
            992,
            987
        ],
        "y": [
            372,
            372,
            380,
            380
        ]
    },
    "5": {
        "x": [
            1012,
            1019,
            1019,
            1012
        ],
        "y": [
            376,
            376,
            385,
            385
        ]
    },
    "6": {
        "x": [
            39,
            48,
            48,
            39
        ],
        "y": [
            376,
            376,
            392,
            392
        ]
    },
    "7": {
        "x": [
            61,
            71,
            71,
            61
        ],
        "y": [
            378,
            378,
            391,
            391
        ]
    },
    "8": {
        "x": [
            916,
            922,
            922,
            916
        ],
        "y": [
            383,
            383,
            393,
            393
        ]
    },
    "9": {
        "x": [
            935,
            940,
            940,
            935
        ],
        "y": [
            390,
            390,
            397,
            397
        ]
    },
    "10": {
        "x": [
            877,
            884,
            884,
            877
        ],
        "y": [
            349,
            349,
            356,
            356
        ]
    },
    "11": {
        "x": [
            892,
            898,
            898,
            892
        ],
        "y": [
            382,
            382,
            389,
            389
        ]
    },
    "12": {
        "x": [
            896,
            902,
            902,
            896
        ],
        "y": [
            378,
            378,
            386,
            386
        ]
    },
    "13": {
        "x": [
            1005,
            1011,
            1011,
            1005
        ],
        "y": [
            347,
            347,
            354,
            354
        ]
    },
    "14": {
        "x": [
            1007,
            1011,
            1011,
            1007
        ],
        "y": [
            367,
            367,
            374,
            374
        ]
    },
    "15": {
        "x": [
            925,
            930,
            930,
            925
        ],
        "y": [
            351,
            351,
            357,
            357
        ]
    }
}