{
    "0": {
        "x": [
            193,
            214,
            214,
            193
        ],
        "y": [
            114,
            114,
            146,
            146
        ]
    },
    "1": {
        "x": [
            451,
            472,
            472,
            451
        ],
        "y": [
            122,
            122,
            154,
            154
        ]
    },
    "2": {
        "x": [
            393,
            411,
            411,
            393
        ],
        "y": [
            105,
            105,
            131,
            131
        ]
    },
    "3": {
        "x": [
            509,
            534,
            534,
            509
        ],
        "y": [
            104,
            104,
            155,
            155
        ]
    },
    "4": {
        "x": [
            557,
            657,
            657,
            557
        ],
        "y": [
            89,
            89,
            214,
            214
        ]
    },
    "5": {
        "x": [
            676,
            706,
            706,
            676
        ],
        "y": [
            135,
            135,
            182,
            182
        ]
    },
    "6": {
        "x": [
            795,
            803,
            803,
            795
        ],
        "y": [
            114,
            114,
            126,
            126
        ]
    },
    "7": {
        "x": [
            877,
            925,
            925,
            877
        ],
        "y": [
            43,
            43,
            108,
            108
        ]
    },
    "8": {
        "x": [
            998,
            1024,
            1024,
            998
        ],
        "y": [
            94,
            94,
            139,
            139
        ]
    }
}