{
    "0": {
        "x": [
            689,
            741,
            741,
            689
        ],
        "y": [
            147,
            147,
            212,
            212
        ]
    },
    "1": {
        "x": [
            662,
            685,
            685,
            662
        ],
        "y": [
            170,
            170,
            198,
            198
        ]
    },
    "2": {
        "x": [
            636,
            649,
            649,
            636
        ],
        "y": [
            155,
            155,
            171,
            171
        ]
    },
    "3": {
        "x": [
            582,
            601,
            601,
            582
        ],
        "y": [
            133,
            133,
            157,
            157
        ]
    },
    "4": {
        "x": [
            530,
            583,
            583,
            530
        ],
        "y": [
            157,
            157,
            216,
            216
        ]
    },
    "5": {
        "x": [
            365,
            412,
            412,
            365
        ],
        "y": [
            96,
            96,
            151,
            151
        ]
    },
    "6": {
        "x": [
            249,
            297,
            297,
            249
        ],
        "y": [
            146,
            146,
            204,
            204
        ]
    },
    "7": {
        "x": [
            111,
            168,
            168,
            111
        ],
        "y": [
            148,
            148,
            211,
            211
        ]
    },
    "8": {
        "x": [
            13,
            70,
            70,
            13
        ],
        "y": [
            117,
            117,
            203,
            203
        ]
    },
    "9": {
        "x": [
            952,
            964,
            964,
            952
        ],
        "y": [
            167,
            167,
            183,
            183
        ]
    },
    "10": {
        "x": [
            991,
            1024,
            1024,
            991
        ],
        "y": [
            150,
            150,
            251,
            251
        ]
    }
}