{
    "0": {
        "x": [
            309,
            353,
            353,
            309
        ],
        "y": [
            258,
            258,
            310,
            310
        ]
    },
    "1": {
        "x": [
            251,
            284,
            284,
            251
        ],
        "y": [
            317,
            317,
            360,
            360
        ]
    },
    "2": {
        "x": [
            334,
            379,
            379,
            334
        ],
        "y": [
            330,
            330,
            373,
            373
        ]
    },
    "3": {
        "x": [
            372,
            402,
            402,
            372
        ],
        "y": [
            214,
            214,
            253,
            253
        ]
    },
    "4": {
        "x": [
            598,
            624,
            624,
            598
        ],
        "y": [
            261,
            261,
            290,
            290
        ]
    },
    "5": {
        "x": [
            614,
            629,
            629,
            614
        ],
        "y": [
            203,
            203,
            218,
            218
        ]
    },
    "6": {
        "x": [
            474,
            513,
            513,
            474
        ],
        "y": [
            232,
            232,
            272,
            272
        ]
    },
    "7": {
        "x": [
            420,
            435,
            435,
            420
        ],
        "y": [
            251,
            251,
            268,
            268
        ]
    },
    "8": {
        "x": [
            475,
            513,
            513,
            475
        ],
        "y": [
            305,
            305,
            350,
            350
        ]
    },
    "9": {
        "x": [
            646,
            689,
            689,
            646
        ],
        "y": [
            290,
            290,
            344,
            344
        ]
    },
    "10": {
        "x": [
            833,
            876,
            876,
            833
        ],
        "y": [
            412,
            412,
            480,
            480
        ]
    },
    "11": {
        "x": [
            876,
            930,
            930,
            876
        ],
        "y": [
            295,
            295,
            348,
            348
        ]
    },
    "12": {
        "x": [
            832,
            876,
            876,
            832
        ],
        "y": [
            293,
            293,
            355,
            355
        ]
    },
    "13": {
        "x": [
            754,
            802,
            802,
            754
        ],
        "y": [
            334,
            334,
            392,
            392
        ]
    },
    "14": {
        "x": [
            732,
            762,
            762,
            732
        ],
        "y": [
            261,
            261,
            297,
            297
        ]
    },
    "15": {
        "x": [
            773,
            799,
            799,
            773
        ],
        "y": [
            269,
            269,
            303,
            303
        ]
    },
    "16": {
        "x": [
            885,
            905,
            905,
            885
        ],
        "y": [
            79,
            79,
            104,
            104
        ]
    },
    "17": {
        "x": [
            327,
            392,
            392,
            327
        ],
        "y": [
            508,
            508,
            551,
            551
        ]
    },
    "18": {
        "x": [
            968,
            1010,
            1010,
            968
        ],
        "y": [
            281,
            281,
            331,
            331
        ]
    },
    "19": {
        "x": [
            909,
            934,
            934,
            909
        ],
        "y": [
            191,
            191,
            217,
            217
        ]
    }
}