{
    "0": {
        "x": [
            679,
            740,
            740,
            679
        ],
        "y": [
            155,
            155,
            221,
            221
        ]
    },
    "1": {
        "x": [
            771,
            845,
            845,
            771
        ],
        "y": [
            207,
            207,
            264,
            264
        ]
    },
    "2": {
        "x": [
            546,
            571,
            571,
            546
        ],
        "y": [
            139,
            139,
            179,
            179
        ]
    },
    "3": {
        "x": [
            318,
            350,
            350,
            318
        ],
        "y": [
            146,
            146,
            185,
            185
        ]
    },
    "4": {
        "x": [
            63,
            84,
            84,
            63
        ],
        "y": [
            185,
            185,
            217,
            217
        ]
    }
}