{
    "0": {
        "x": [
            592,
            668,
            668,
            592
        ],
        "y": [
            98,
            98,
            210,
            210
        ]
    },
    "1": {
        "x": [
            772,
            848,
            848,
            772
        ],
        "y": [
            38,
            38,
            144,
            144
        ]
    },
    "2": {
        "x": [
            120,
            194,
            194,
            120
        ],
        "y": [
            112,
            112,
            206,
            206
        ]
    }
}