{
    "0": {
        "x": [
            308,
            469,
            469,
            308
        ],
        "y": [
            755,
            755,
            934,
            934
        ]
    },
    "1": {
        "x": [
            123,
            168,
            168,
            123
        ],
        "y": [
            702,
            702,
            759,
            759
        ]
    },
    "2": {
        "x": [
            867,
            932,
            932,
            867
        ],
        "y": [
            711,
            711,
            795,
            795
        ]
    },
    "3": {
        "x": [
            561,
            734,
            734,
            561
        ],
        "y": [
            463,
            463,
            699,
            699
        ]
    },
    "4": {
        "x": [
            1001,
            1024,
            1024,
            1001
        ],
        "y": [
            758,
            758,
            800,
            800
        ]
    },
    "5": {
        "x": [
            55,
            105,
            105,
            55
        ],
        "y": [
            814,
            814,
            871,
            871
        ]
    },
    "6": {
        "x": [
            1011,
            1024,
            1024,
            1011
        ],
        "y": [
            712,
            712,
            735,
            735
        ]
    }
}