{
    "0": {
        "x": [
            791,
            810,
            810,
            791
        ],
        "y": [
            61,
            61,
            85,
            85
        ]
    },
    "1": {
        "x": [
            106,
            125,
            125,
            106
        ],
        "y": [
            1012,
            1012,
            1053,
            1053
        ]
    },
    "2": {
        "x": [
            59,
            82,
            82,
            59
        ],
        "y": [
            1049,
            1049,
            1074,
            1074
        ]
    },
    "3": {
        "x": [
            135,
            159,
            159,
            135
        ],
        "y": [
            1204,
            1204,
            1231,
            1231
        ]
    },
    "4": {
        "x": [
            368,
            380,
            380,
            368
        ],
        "y": [
            1053,
            1053,
            1075,
            1075
        ]
    },
    "5": {
        "x": [
            536,
            559,
            559,
            536
        ],
        "y": [
            1073,
            1073,
            1103,
            1103
        ]
    },
    "6": {
        "x": [
            676,
            689,
            689,
            676
        ],
        "y": [
            1073,
            1073,
            1089,
            1089
        ]
    },
    "7": {
        "x": [
            685,
            701,
            701,
            685
        ],
        "y": [
            1069,
            1069,
            1088,
            1088
        ]
    },
    "8": {
        "x": [
            777,
            794,
            794,
            777
        ],
        "y": [
            1065,
            1065,
            1088,
            1088
        ]
    },
    "9": {
        "x": [
            888,
            904,
            904,
            888
        ],
        "y": [
            1059,
            1059,
            1086,
            1086
        ]
    },
    "10": {
        "x": [
            843,
            852,
            852,
            843
        ],
        "y": [
            1035,
            1035,
            1046,
            1046
        ]
    },
    "11": {
        "x": [
            836,
            846,
            846,
            836
        ],
        "y": [
            1036,
            1036,
            1046,
            1046
        ]
    },
    "12": {
        "x": [
            563,
            576,
            576,
            563
        ],
        "y": [
            140,
            140,
            160,
            160
        ]
    },
    "13": {
        "x": [
            349,
            375,
            375,
            349
        ],
        "y": [
            912,
            912,
            942,
            942
        ]
    },
    "14": {
        "x": [
            632,
            656,
            656,
            632
        ],
        "y": [
            891,
            891,
            918,
            918
        ]
    },
    "15": {
        "x": [
            375,
            398,
            398,
            375
        ],
        "y": [
            663,
            663,
            689,
            689
        ]
    },
    "16": {
        "x": [
            565,
            579,
            579,
            565
        ],
        "y": [
            868,
            868,
            894,
            894
        ]
    },
    "17": {
        "x": [
            271,
            292,
            292,
            271
        ],
        "y": [
            962,
            962,
            983,
            983
        ]
    },
    "18": {
        "x": [
            57,
            80,
            80,
            57
        ],
        "y": [
            96,
            96,
            121,
            121
        ]
    },
    "19": {
        "x": [
            106,
            125,
            125,
            106
        ],
        "y": [
            1013,
            1013,
            1053,
            1053
        ]
    },
    "20": {
        "x": [
            368,
            380,
            380,
            368
        ],
        "y": [
            1053,
            1053,
            1082,
            1082
        ]
    },
    "21": {
        "x": [
            674,
            689,
            689,
            674
        ],
        "y": [
            1073,
            1073,
            1089,
            1089
        ]
    },
    "22": {
        "x": [
            776,
            794,
            794,
            776
        ],
        "y": [
            1065,
            1065,
            1088,
            1088
        ]
    },
    "23": {
        "x": [
            468,
            488,
            488,
            468
        ],
        "y": [
            76,
            76,
            103,
            103
        ]
    },
    "24": {
        "x": [
            915,
            928,
            928,
            915
        ],
        "y": [
            133,
            133,
            150,
            150
        ]
    },
    "25": {
        "x": [
            157,
            176,
            176,
            157
        ],
        "y": [
            98,
            98,
            119,
            119
        ]
    },
    "26": {
        "x": [
            335,
            361,
            361,
            335
        ],
        "y": [
            695,
            695,
            723,
            723
        ]
    },
    "27": {
        "x": [
            371,
            394,
            394,
            371
        ],
        "y": [
            697,
            697,
            724,
            724
        ]
    },
    "28": {
        "x": [
            465,
            489,
            489,
            465
        ],
        "y": [
            723,
            723,
            740,
            740
        ]
    },
    "29": {
        "x": [
            445,
            469,
            469,
            445
        ],
        "y": [
            721,
            721,
            745,
            745
        ]
    },
    "30": {
        "x": [
            318,
            342,
            342,
            318
        ],
        "y": [
            692,
            692,
            717,
            717
        ]
    },
    "31": {
        "x": [
            277,
            304,
            304,
            277
        ],
        "y": [
            705,
            705,
            733,
            733
        ]
    },
    "32": {
        "x": [
            298,
            326,
            326,
            298
        ],
        "y": [
            765,
            765,
            793,
            793
        ]
    },
    "33": {
        "x": [
            194,
            218,
            218,
            194
        ],
        "y": [
            729,
            729,
            749,
            749
        ]
    },
    "34": {
        "x": [
            245,
            269,
            269,
            245
        ],
        "y": [
            729,
            729,
            747,
            747
        ]
    },
    "35": {
        "x": [
            327,
            355,
            355,
            327
        ],
        "y": [
            779,
            779,
            798,
            798
        ]
    },
    "36": {
        "x": [
            367,
            386,
            386,
            367
        ],
        "y": [
            885,
            885,
            907,
            907
        ]
    }
}