{
    "0": {
        "x": [
            340,
            396,
            396,
            340
        ],
        "y": [
            88,
            88,
            144,
            144
        ]
    },
    "1": {
        "x": [
            474,
            532,
            532,
            474
        ],
        "y": [
            106,
            106,
            186,
            186
        ]
    },
    "2": {
        "x": [
            636,
            698,
            698,
            636
        ],
        "y": [
            112,
            112,
            188,
            188
        ]
    }
}