{
    "0": {
        "x": [
            153,
            272,
            272,
            153
        ],
        "y": [
            103,
            103,
            211,
            211
        ]
    },
    "1": {
        "x": [
            272,
            340,
            340,
            272
        ],
        "y": [
            137,
            137,
            246,
            246
        ]
    },
    "2": {
        "x": [
            418,
            480,
            480,
            418
        ],
        "y": [
            122,
            122,
            210,
            210
        ]
    },
    "3": {
        "x": [
            615,
            672,
            672,
            615
        ],
        "y": [
            225,
            225,
            293,
            293
        ]
    },
    "4": {
        "x": [
            790,
            843,
            843,
            790
        ],
        "y": [
            195,
            195,
            266,
            266
        ]
    },
    "5": {
        "x": [
            945,
            989,
            989,
            945
        ],
        "y": [
            180,
            180,
            237,
            237
        ]
    }
}