{
    "0": {
        "x": [
            196,
            228,
            228,
            196
        ],
        "y": [
            115,
            115,
            158,
            158
        ]
    },
    "1": {
        "x": [
            260,
            287,
            287,
            260
        ],
        "y": [
            109,
            109,
            146,
            146
        ]
    },
    "2": {
        "x": [
            337,
            369,
            369,
            337
        ],
        "y": [
            94,
            94,
            135,
            135
        ]
    },
    "3": {
        "x": [
            423,
            459,
            459,
            423
        ],
        "y": [
            103,
            103,
            152,
            152
        ]
    },
    "4": {
        "x": [
            84,
            127,
            127,
            84
        ],
        "y": [
            146,
            146,
            184,
            184
        ]
    },
    "5": {
        "x": [
            38,
            82,
            82,
            38
        ],
        "y": [
            201,
            201,
            237,
            237
        ]
    },
    "6": {
        "x": [
            65,
            102,
            102,
            65
        ],
        "y": [
            253,
            253,
            293,
            293
        ]
    },
    "7": {
        "x": [
            136,
            174,
            174,
            136
        ],
        "y": [
            282,
            282,
            331,
            331
        ]
    },
    "8": {
        "x": [
            238,
            272,
            272,
            238
        ],
        "y": [
            292,
            292,
            339,
            339
        ]
    },
    "9": {
        "x": [
            337,
            372,
            372,
            337
        ],
        "y": [
            290,
            290,
            340,
            340
        ]
    },
    "10": {
        "x": [
            413,
            453,
            453,
            413
        ],
        "y": [
            293,
            293,
            343,
            343
        ]
    },
    "11": {
        "x": [
            497,
            525,
            525,
            497
        ],
        "y": [
            49,
            49,
            89,
            89
        ]
    },
    "12": {
        "x": [
            557,
            588,
            588,
            557
        ],
        "y": [
            146,
            146,
            195,
            195
        ]
    },
    "13": {
        "x": [
            967,
            1006,
            1006,
            967
        ],
        "y": [
            332,
            332,
            374,
            374
        ]
    },
    "14": {
        "x": [
            954,
            989,
            989,
            954
        ],
        "y": [
            245,
            245,
            290,
            290
        ]
    },
    "15": {
        "x": [
            939,
            977,
            977,
            939
        ],
        "y": [
            173,
            173,
            218,
            218
        ]
    },
    "16": {
        "x": [
            850,
            885,
            885,
            850
        ],
        "y": [
            166,
            166,
            209,
            209
        ]
    },
    "17": {
        "x": [
            764,
            801,
            801,
            764
        ],
        "y": [
            162,
            162,
            208,
            208
        ]
    },
    "18": {
        "x": [
            697,
            734,
            734,
            697
        ],
        "y": [
            199,
            199,
            247,
            247
        ]
    },
    "19": {
        "x": [
            618,
            653,
            653,
            618
        ],
        "y": [
            225,
            225,
            276,
            276
        ]
    },
    "20": {
        "x": [
            500,
            528,
            528,
            500
        ],
        "y": [
            523,
            523,
            563,
            563
        ]
    }
}