{
    "0": {
        "x": [
            11,
            104,
            104,
            11
        ],
        "y": [
            400,
            400,
            594,
            594
        ]
    },
    "1": {
        "x": [
            225,
            326,
            326,
            225
        ],
        "y": [
            487,
            487,
            621,
            621
        ]
    },
    "2": {
        "x": [
            307,
            630,
            630,
            307
        ],
        "y": [
            57,
            57,
            512,
            512
        ]
    }
}